mockingbird/__base.py
mockingbird/__command_line.py
mockingbird/__init__.py
mockingbird/_default_config.yml
mockingbird/_meta_data.py
mockingbird/mb_wrappers.py
mockingbird/mockaroo_csv_api/__init__.py
mockingbird/random_data_generator/__init__.py
mockingbird/sized_config_maker/__init__.py
mockingbird/structured_data_document/__base.py
mockingbird/structured_data_document/__init__.py
mockingbird/structured_data_document/csv_document.py
mockingbird/structured_data_document/json_document.py
mockingbird/structured_data_document/log_document.py
mockingbird/structured_data_document/ods_document.py
mockingbird/structured_data_document/yaml_document.py
mockingbird/structured_data_document/panda_documents/__base.py
mockingbird/structured_data_document/panda_documents/__init__.py
mockingbird/structured_data_document/panda_documents/avro_document.py
mockingbird/structured_data_document/panda_documents/parquet_document.py
mockingbird/structured_data_document/panda_documents/xlsx_document.py
mockingbird/unstructured_data_document/__base.py
mockingbird/unstructured_data_document/__init__.py
mockingbird/unstructured_data_document/docx_document.py
mockingbird/unstructured_data_document/pdf_document.py
mockingbird/unstructured_data_document/pptx_document.py
mockingbird/unstructured_data_document/txt_document.py
mockingbird-1.1.2.dist-info/LICENSE
mockingbird-1.1.2.dist-info/METADATA
mockingbird-1.1.2.dist-info/WHEEL
mockingbird-1.1.2.dist-info/entry_points.txt
mockingbird-1.1.2.dist-info/top_level.txt
mockingbird-1.1.2.dist-info/RECORD
