Metadata-Version: 2.1
Name: mockingbird
Version: 1.1.2
Summary: Generate mock documents in various formats (CSV, DOCX, PDF, TXT, and more) that embed seed data and can be used to test data classification software.
Home-page: https://www.github.com/openraven/mockingbird
Author: Open Raven Team
Author-email: opensource@openraven.com
License: apache
Classifier: Development Status :: 5 - Production/Stable
Classifier: License :: OSI Approved :: Apache Software License
Classifier: Programming Language :: Python :: 3.8
License-File: LICENSE
Requires-Dist: openpyxl ==3.1.2
Requires-Dist: RandomWords ==0.3.0
Requires-Dist: pyyaml ==6.0.1
Requires-Dist: pyexcel-ods ==0.6.0
Requires-Dist: python-docx ==0.8.11
Requires-Dist: requests ==2.25.0
Requires-Dist: pyarrow ==14.0.2
Requires-Dist: numpy >=1.19.5
Requires-Dist: reportlab ==3.6.12
Requires-Dist: pandas ==1.5.2
Requires-Dist: avro ==1.11.1
Requires-Dist: python-pptx ==0.6.21
Requires-Dist: pyspark ==3.3.1
